rr_process/__init__.py
rr_process/delete_unused_libs.py
rr_delete_unused_packages-0.1.dist-info/METADATA
rr_delete_unused_packages-0.1.dist-info/WHEEL
rr_delete_unused_packages-0.1.dist-info/top_level.txt
rr_delete_unused_packages-0.1.dist-info/RECORD
