Metadata-Version: 2.1
Name: rr-delete-unused-packages
Version: 0.1
Summary: rr-delete-unused-packages
Home-page: https://upload.pypi.org/legacy/
Author: Yossi Arar
Author-email: yossiarar@gmail.com
Classifier: Programming Language :: Python :: 3
Classifier: Operating System :: OS Independent
Requires-Python: >=3.10
